<?xml version = '1.0' encoding = 'UTF-8'?>
<TableProxyOraclev11g class="oracle.dbtools.crest.model.design.storage.oracle.v11g.TableProxyOraclev11g" name="IMS_STATE_ABBRV" directorySegmentName="seg_0" id="5191E6EB-4E9B-4B79-D31F-352A78F3A843">
<createdBy>Justin</createdBy>
<createdTime>2016-08-16 02:49:21 UTC</createdTime>
<ownerDesignName>IMS Physical Data Model</ownerDesignName>
<schemaObject>B46FE20C-0185-DEC2-CCE6-B0C10561E73A</schemaObject>
<logging>YES</logging>
<partitionedRowMovement>DISABLE</partitionedRowMovement>
<segment>8C8E1B4B-382A-2976-1139-0B2ABD1FCF68</segment>
<tableSpace>F7CC4B95-B256-4CA6-3FC8-E3BDEB49DA58</tableSpace>
<temporaryChanged>false</temporaryChanged>
<accessDriverType>oracle_loader</accessDriverType>
<rejectLimit></rejectLimit>
<columnProxies itemClass="oracle.dbtools.crest.model.design.storage.oracle.v12c.ColumnProxyOraclev12c">
<ColumnProxy name="STATE_ABBRV" id="24E4F0D0-3510-4522-73F2-199FBCF9A378">
<createdBy>Justin</createdBy>
<createdTime>2016-08-16 02:49:21 UTC</createdTime>
<ownerDesignName>IMS Physical Data Model</ownerDesignName>
</ColumnProxy>
<ColumnProxy name="STATE_NAME" id="A5058B12-3D92-C185-358F-BC95CE6369E2">
<createdBy>Justin</createdBy>
<createdTime>2016-08-16 02:49:21 UTC</createdTime>
<ownerDesignName>IMS Physical Data Model</ownerDesignName>
</ColumnProxy>
<ColumnProxy name="ABBRV_ID" id="B974376F-6740-AA2A-06EC-F47358B1C643">
<createdBy>Justin</createdBy>
<createdTime>2016-08-16 02:49:21 UTC</createdTime>
<ownerDesignName>IMS Physical Data Model</ownerDesignName>
</ColumnProxy>
</columnProxies>
<primaryKeys>
<PrimaryKey class="oracle.dbtools.crest.model.design.storage.oracle.v10g.PKProxyOraclev10g" name="IMS_STATE_ABBRV_PK" id="B1BA1C18-6E8A-0028-3DDD-BD5CDBEEA3E1">
<createdBy>Justin</createdBy>
<createdTime>2016-08-16 02:49:21 UTC</createdTime>
<ownerDesignName>IMS Physical Data Model</ownerDesignName>
<schemaObject>B46FE20C-0185-DEC2-CCE6-B0C10561E73A</schemaObject>
<segment>0EAB6280-8018-E44B-121F-F156154D1837</segment>
<tableSpace>F7CC4B95-B256-4CA6-3FC8-E3BDEB49DA58</tableSpace>
<indexSegment>0EAB6280-8018-E44B-121F-F156154D1837</indexSegment>
<indexSort>SORTED</indexSort>
<usingIndex>BY INDEX NAME</usingIndex>
</PrimaryKey>
</primaryKeys>
</TableProxyOraclev11g>